statsutil/__init__.py
statsutil/a.py
bfg_statsutil-0.1.1.dist-info/METADATA
bfg_statsutil-0.1.1.dist-info/WHEEL
bfg_statsutil-0.1.1.dist-info/RECORD
