Metadata-Version: 2.4
Name: bfg-statsutil
Version: 0.1.1
Summary: A simple library for sending metrics directly to Datadog without requiring an agent installation
Author-email: Lei Zhao <8961794+leizha@users.noreply.github.com>
Requires-Python: >=3.13
Requires-Dist: requests
